ymfm/__init__.py
ymfm/_core.cpython-312-x86_64-linux-gnu.so
ymfm/_core.pyi
ymfm/_types.py
ymfm/_version.py
ymfm/py.typed
ymfm/bindings/chips_opl.cpp
ymfm/bindings/chips_opm.cpp
ymfm/bindings/chips_opn.cpp
ymfm/bindings/chips_opq.cpp
ymfm/bindings/chips_opz.cpp
ymfm/bindings/chips_ssg.cpp
ymfm/bindings/common.hpp
ymfm/bindings/interface.cpp
ymfm/bindings/interface.hpp
ymfm/bindings/module.cpp
ymfm_py-0.2.0.dist-info/METADATA
ymfm_py-0.2.0.dist-info/WHEEL
ymfm_py-0.2.0.dist-info/RECORD
ymfm_py-0.2.0.dist-info/licenses/LICENSE
