Metadata-Version: 2.2
Name: ymfm-py
Version: 0.2.0
Summary: Python bindings for ymfm FM synthesis library
Keywords: fm,synthesis,yamaha,emulation,audio,ymfm
Author: ymfm-py contributors
License: BSD-3-Clause
Classifier: Development Status :: 3 - Alpha
Classifier: Intended Audience :: Developers
Classifier: License :: OSI Approved :: BSD License
Classifier: Programming Language :: Python :: 3
Classifier: Programming Language :: Python :: 3.11
Classifier: Programming Language :: Python :: 3.12
Classifier: Programming Language :: Python :: 3.13
Classifier: Programming Language :: Python :: 3.14
Classifier: Programming Language :: C++
Classifier: Topic :: Multimedia :: Sound/Audio :: Sound Synthesis
Project-URL: Homepage, https://github.com/moriyoshi/ymfm-py
Project-URL: Repository, https://github.com/moriyoshi/ymfm-py
Requires-Python: >=3.11
